[
    {
        "id": 3,
        "type": "circle",
        "area": 7425.5,
        "perimeter": 2163.6723449230194,
        "color_rgb": [
            140.76458607883072,
            149.9756798849886,
            173.16281298670182
        ],
        "centroid": [
            1466,
            1398
        ],
        "vertices": 9
    },
    {
        "id": 5,
        "type": "polygon",
        "area": 27132.5,
        "perimeter": 1347.1585041284561,
        "color_rgb": [
            52.093692524072274,
            143.75401204515128,
            203.4971690288146
        ],
        "centroid": [
            833,
            1243
        ],
        "vertices": 8
    },
    {
        "id": 6,
        "type": "polygon",
        "area": 25331.0,
        "perimeter": 905.1757484674454,
        "color_rgb": [
            52.076958973361855,
            145.33155745673733,
            205.19284464320438
        ],
        "centroid": [
            835,
            1245
        ],
        "vertices": 6
    },
    {
        "id": 7,
        "type": "circle",
        "area": 123452.0,
        "perimeter": 4289.850184082985,
        "color_rgb": [
            35.04352439919574,
            79.46241981297673,
            122.67499920211918
        ],
        "centroid": [
            316,
            1677
        ],
        "vertices": 16
    },
    {
        "id": 8,
        "type": "triangle",
        "area": 41491.0,
        "perimeter": 945.7443064451218,
        "color_rgb": [
            40.36285721106787,
            42.1774297514742,
            59.663451667581825
        ],
        "centroid": [
            340,
            1842
        ],
        "vertices": 3
    },
    {
        "id": 9,
        "type": "triangle",
        "area": 41388.5,
        "perimeter": 940.4722323417664,
        "color_rgb": [
            18.32448539971278,
            74.62333652465294,
            132.43312589755863
        ],
        "centroid": [
            204,
            1706
        ],
        "vertices": 3
    },
    {
        "id": 10,
        "type": "polygon",
        "area": 8155.5,
        "perimeter": 440.2914102077484,
        "color_rgb": [
            21.905771072796934,
            96.43738026819923,
            158.97737068965517
        ],
        "centroid": [
            452,
            1680
        ],
        "vertices": 6
    },
    {
        "id": 11,
        "type": "pentagon",
        "area": 8096.5,
        "perimeter": 440.29141068458557,
        "color_rgb": [
            49.21065959242735,
            142.27686000241167,
            203.23332931387918
        ],
        "centroid": [
            452,
            1595
        ],
        "vertices": 5
    },
    {
        "id": 12,
        "type": "polygon",
        "area": 8104.5,
        "perimeter": 438.634556889534,
        "color_rgb": [
            47.470907119624144,
            136.6007709914468,
            197.00734851222745
        ],
        "centroid": [
            452,
            1270
        ],
        "vertices": 6
    },
    {
        "id": 13,
        "type": "pentagon",
        "area": 8121.5,
        "perimeter": 436.63455617427826,
        "color_rgb": [
            43.212937357220156,
            119.72069255741253,
            172.6061079716244
        ],
        "centroid": [
            365,
            1186
        ],
        "vertices": 5
    },
    {
        "id": 14,
        "type": "polygon",
        "area": 32680.0,
        "perimeter": 677.4112504720688,
        "color_rgb": [
            46.63451622687292,
            135.06096451319382,
            197.9148619957537
        ],
        "centroid": [
            613,
            1023
        ],
        "vertices": 8
    },
    {
        "id": 15,
        "type": "polygon",
        "area": 32508.0,
        "perimeter": 674.239676117897,
        "color_rgb": [
            46.79369435296987,
            135.4207830223198,
            198.0247591169655
        ],
        "centroid": [
            613,
            1023
        ],
        "vertices": 8
    },
    {
        "id": 17,
        "type": "polygon",
        "area": 32678.0,
        "perimeter": 675.7543935775757,
        "color_rgb": [
            75.10337296772629,
            168.12263406940065,
            223.2496966755642
        ],
        "centroid": [
            1433,
            204
        ],
        "vertices": 8
    },
    {
        "id": 18,
        "type": "polygon",
        "area": 32518.0,
        "perimeter": 673.4112491607666,
        "color_rgb": [
            75.14683289642139,
            168.45208193623117,
            223.7664146802414
        ],
        "centroid": [
            1433,
            204
        ],
        "vertices": 8
    },
    {
        "id": 19,
        "type": "polygon",
        "area": 32673.5,
        "perimeter": 677.1686103343964,
        "color_rgb": [
            38.05502972940177,
            117.02232738745298,
            182.07838854507946
        ],
        "centroid": [
            1842,
            204
        ],
        "vertices": 8
    },
    {
        "id": 20,
        "type": "polygon",
        "area": 32505.0,
        "perimeter": 674.2396770715714,
        "color_rgb": [
            38.09380050620559,
            117.29430061293569,
            182.4597017656207
        ],
        "centroid": [
            1842,
            204
        ],
        "vertices": 8
    },
    {
        "id": 22,
        "type": "circle",
        "area": 642870.5,
        "perimeter": 19789.05708503723,
        "color_rgb": [
            55.16456533719776,
            130.7921671811892,
            179.90741818170653
        ],
        "centroid": [
            915,
            980
        ],
        "vertices": 13
    },
    {
        "id": 23,
        "type": "triangle",
        "area": 41384.0,
        "perimeter": 938.3717310428619,
        "color_rgb": [
            55.067723170468966,
            157.4739185598353,
            212.65439398654632
        ],
        "centroid": [
            887,
            1842
        ],
        "vertices": 3
    },
    {
        "id": 24,
        "type": "pentagon",
        "area": 8041.5,
        "perimeter": 434.63455641269684,
        "color_rgb": [
            21.613647401651285,
            94.12008256435162,
            154.08814958717824
        ],
        "centroid": [
            775,
            1680
        ],
        "vertices": 5
    },
    {
        "id": 25,
        "type": "triangle",
        "area": 41588.0,
        "perimeter": 941.2001581192017,
        "color_rgb": [
            38.95133164991186,
            45.37236171327839,
            79.30358759350136
        ],
        "centroid": [
            1023,
            1706
        ],
        "vertices": 3
    },
    {
        "id": 26,
        "type": "circle",
        "area": 110291.5,
        "perimeter": 2731.073506593704,
        "color_rgb": [
            50.36352294961317,
            142.8885907124522,
            192.73597623364267
        ],
        "centroid": [
            1320,
            1722
        ],
        "vertices": 11
    },
    {
        "id": 27,
        "type": "pentagon",
        "area": 16745.5,
        "perimeter": 677.3696191310883,
        "color_rgb": [
            49.88696519748812,
            142.40947238687718,
            199.23598802746642
        ],
        "centroid": [
            818,
            1592
        ],
        "vertices": 5
    },
    {
        "id": 28,
        "type": "pentagon",
        "area": 16599.0,
        "perimeter": 669.6122603416443,
        "color_rgb": [
            56.18593083846518,
            152.26213879677877,
            211.25817148270963
        ],
        "centroid": [
            1181,
            1228
        ],
        "vertices": 5
    },
    {
        "id": 29,
        "type": "pentagon",
        "area": 7985.0,
        "perimeter": 435.2203446626663,
        "color_rgb": [
            57.11369193154034,
            151.19645476772615,
            213.25110024449876
        ],
        "centroid": [
            1185,
            861
        ],
        "vertices": 5
    },
    {
        "id": 30,
        "type": "polygon",
        "area": 8059.5,
        "perimeter": 438.29140996932983,
        "color_rgb": [
            59.073410054512415,
            156.34948516050878,
            221.28358570563296
        ],
        "centroid": [
            861,
            861
        ],
        "vertices": 6
    },
    {
        "id": 31,
        "type": "pentagon",
        "area": 7940.0,
        "perimeter": 431.220343708992,
        "color_rgb": [
            44.60137710561908,
            125.06098610598795,
            181.41534489118405
        ],
        "centroid": [
            366,
            861
        ],
        "vertices": 5
    },
    {
        "id": 32,
        "type": "triangle",
        "area": 41532.0,
        "perimeter": 942.0285851955414,
        "color_rgb": [
            45.24197318830208,
            51.246362291875386,
            73.50555794093793
        ],
        "centroid": [
            1023,
            750
        ],
        "vertices": 3
    },
    {
        "id": 33,
        "type": "rectangle",
        "area": 125470.0,
        "perimeter": 1543.2286972999573,
        "color_rgb": [
            61.354150968837,
            162.6061516985382,
            220.25372980432903
        ],
        "centroid": [
            750,
            659
        ],
        "vertices": 4
    },
    {
        "id": 34,
        "type": "pentagon",
        "area": 66638.0,
        "perimeter": 1343.557576060295,
        "color_rgb": [
            56.28905029097025,
            154.03499084671597,
            211.2666210242748
        ],
        "centroid": [
            1212,
            567
        ],
        "vertices": 5
    },
    {
        "id": 35,
        "type": "triangle",
        "area": 41365.0,
        "perimeter": 937.5433039665222,
        "color_rgb": [
            74.38374766489439,
            164.09630215069214,
            217.36719835225367
        ],
        "centroid": [
            614,
            340
        ],
        "vertices": 3
    },
    {
        "id": 36,
        "type": "triangle",
        "area": 41469.0,
        "perimeter": 939.2001565694809,
        "color_rgb": [
            61.0858139423766,
            64.49560418557982,
            81.00408524057528
        ],
        "centroid": [
            477,
            204
        ],
        "vertices": 3
    },
    {
        "id": 37,
        "type": "triangle",
        "area": 41434.0,
        "perimeter": 942.3717209100723,
        "color_rgb": [
            43.774704124327556,
            128.12327555289897,
            190.16633592349072
        ],
        "centroid": [
            340,
            203
        ],
        "vertices": 3
    }
]